legumes/__init__.py
legumes/status_1.py
legumes/_clique/__init__.py
legumes/_clique/group/__init__.py
legumes/_status/status.proc.py
legumes/goals/human/FDA.py
legumes/goals/human/FDA_v1.py
legumes/goals/human/FDA_v2.py
legumes/goals/human/FDA_v3.py
legumes/goals/human/parse_FDA.proc.py
legumes/recipe_with_goals/formulate.py
legumes/recipe_with_goals/_status/0_1_basics/status_1.py
legumes/recipe_with_goals/_status/1_1_recipe/status_1.py
legumes/recipe_with_goals/_status/1_2_recipe/status_1.py
legumes/recipe_with_goals/_status/1_3_recipe_prefomulated/status_1.py
legumes/recipe_with_goals/_status/2_food/status_1.py
legumes/recipe_with_goals/modules/find_goal.py
legumes-2.3.12.dist-info/METADATA
legumes-2.3.12.dist-info/WHEEL
legumes-2.3.12.dist-info/top_level.txt
legumes-2.3.12.dist-info/RECORD
