Metadata-Version: 2.1
Name: legumes
Version: 2.3.12
Summary: nutrition goals
License: 
Requires-Dist: apoplast
Requires-Dist: volts
Requires-Dist: click
Requires-Dist: rich
